<col:collection xmlns="http://cnx.rice.edu/collxml" xmlns:md="http://cnx.rice.edu/mdml" xmlns:col="http://cnx.rice.edu/collxml" xml:lang="en" type="Course">  <metadata xmlns:md="http://cnx.rice.edu/mdml" mdml-version="0.5">  <md:content-id>col10849</md:content-id>  <md:title>Triết học Mác - Lênin trong sự nghiệp đổi mới xã hội</md:title>      <md:license url="http://creativecommons.org/licenses/by/3.0/">Creative Commons Attribution License 3.0</md:license>  <md:language>vi</md:language>              <md:uuid>293d9a34-27dd-4e4a-8b1f-40f5e72b5f6e</md:uuid>
<md:slug>triet-hoc-mac-lenin-trong-su-nghiep-doi-moi-xa-hoi</md:slug>
</metadata>  <col:content>                        <col:subcollection>        <md:title>phần 1:Đối tượng và nhiệm vụ</md:title>                                <col:content>                    <col:module document="m29951"/>                          </col:content>      </col:subcollection>                            <col:subcollection>        <md:title>Phần2:Quan điểm của Mac - Lênin trong giải quyết vấn đề tôn giáo  </md:title>                                <col:content>                    <col:module document="m27718"/>                            <col:module document="m28095"/>                            <col:module document="m28085"/>                            <col:module document="m27605"/>                            <col:module document="m27984"/>                          </col:content>      </col:subcollection>      </col:content></col:collection>